[
{"name":"A","zeronAssingmentData1":4000,"zeronAssingmentData2":2400,"zeronAssingmentData3":2400},
{"name":"B","zeronAssingmentData1":3000,"zeronAssingmentData2":1398,"zeronAssingmentData3":2210},
{"name":"C","zeronAssingmentData1":2000,"zeronAssingmentData2":9800,"zeronAssingmentData3":2290},
{"name":"D","zeronAssingmentData1":2780,"zeronAssingmentData2":3908,"zeronAssingmentData3":2000},
{"name":"E","zeronAssingmentData1":1890,"zeronAssingmentData2":4800,"zeronAssingmentData3":2181},
{"name":"F","zeronAssingmentData1":2390,"zeronAssingmentData2":3800,"zeronAssingmentData3":2500},
{"name":"G","zeronAssingmentData1":3490,"zeronAssingmentData2":4300,"zeronAssingmentData3":2100}
]
